astrostreampy/__init__.py
astrostreampy/argutils.py
astrostreampy/utilities.py
astrostreampy/BuildModel/__init__.py
astrostreampy/BuildModel/aperture.py
astrostreampy/BuildModel/autobuild.py
astrostreampy/BuildModel/box.py
astrostreampy/BuildModel/constants.py
astrostreampy/BuildModel/modify.py
astrostreampy/BuildModel/utilities.py
astrostreampy/Image/__init__.py
astrostreampy/Image/inspect.py
astrostreampy/Image/measure.py
astrostreampy/Image/point.py
astrostreampy/Image/stream.py
astrostreampy/Image/track.py
astrostreampy/Image/utilities.py
astrostreampy-1.9.0.dist-info/LICENSE
astrostreampy-1.9.0.dist-info/METADATA
astrostreampy-1.9.0.dist-info/WHEEL
astrostreampy-1.9.0.dist-info/top_level.txt
astrostreampy-1.9.0.dist-info/RECORD
