Metadata-Version: 2.1
Name: astrostreampy
Version: 1.9.0
Summary: Package to model stellar tidal streams.
Author-email: Jan-Niklas Pippert <jnpippert@usm.lmu.de>
Project-URL: Homepage, https://github.com/jnpippert/streamPy
Project-URL: Bug Tracker, https://github.com/jnpippert/streamPy/issues
Classifier: Programming Language :: Python :: 3
Classifier: License :: OSI Approved :: MIT License
Classifier: Operating System :: OS Independent
Requires-Python: >=3.9
License-File: LICENSE
